utsuho/__init__.py
utsuho/cli.py
utsuho/converters.py
utsuho/maps.py
Utsuho-2.1.0.dist-info/LICENSE
Utsuho-2.1.0.dist-info/METADATA
Utsuho-2.1.0.dist-info/WHEEL
Utsuho-2.1.0.dist-info/entry_points.txt
Utsuho-2.1.0.dist-info/top_level.txt
Utsuho-2.1.0.dist-info/RECORD
