Metadata-Version: 2.1
Name: Utsuho
Version: 2.1.0
Summary: Utsuho is a Python module that facilitates bidirectional conversion between half-width katakana and full-width katakana in Japanese, as well as between hiragana and katakana.
Author-email: Nobuyuki Sekimori <43375309+juno-rmks@users.noreply.github.com>
License: Copyright 2023 Nobuyuki Sekimori
Project-URL: Source Code, https://github.com/juno-rmks/utsuho/
Project-URL: Issue Tracker, https://github.com/juno-rmks/utsuho/issues/
Project-URL: Documentation, https://utsuho.readthedocs.io/
Classifier: License :: OSI Approved :: Apache Software License
Classifier: Operating System :: OS Independent
Classifier: Programming Language :: Python
Requires-Python: >=3.8
License-File: LICENSE
Requires-Dist: click >=8.1.7
Provides-Extra: dev
Requires-Dist: build ; extra == 'dev'
Requires-Dist: twine ; extra == 'dev'
Requires-Dist: autopep8 ; extra == 'dev'
Requires-Dist: isort ; extra == 'dev'
Provides-Extra: docs
Requires-Dist: Sphinx ==5.3.0 ; extra == 'docs'
Requires-Dist: sphinx-intl ==2.1.0 ; extra == 'docs'
Requires-Dist: sphinx-rtd-theme ==1.2.0 ; extra == 'docs'
Requires-Dist: myst-parser ==1.0.0 ; extra == 'docs'
Provides-Extra: test
Requires-Dist: pytest ; extra == 'test'
Requires-Dist: coverage ; extra == 'test'
Requires-Dist: pytest-benchmark ; extra == 'test'
